LICENSE
README.md
requirements.txt
setup.cfg
setup.py
tweet_capture.egg-info/PKG-INFO
tweet_capture.egg-info/SOURCES.txt
tweet_capture.egg-info/dependency_links.txt
tweet_capture.egg-info/entry_points.txt
tweet_capture.egg-info/requires.txt
tweet_capture.egg-info/top_level.txt
tweetcapture/__init__.py
tweetcapture/cli.py
tweetcapture/screenshot.py
tweetcapture/utils/__init__.py
tweetcapture/utils/utils.py
tweetcapture/utils/webdriver.py