Metadata-Version: 2.1
Name: tweet-capture
Version: 0.1.9
Summary: Take a tweet screenshot
Home-page: https://github.com/Xacnio/tweetcapture
Author: Alperen Çetin
Author-email: xacnio@pm.me
License: MIT
Keywords: tweet screenshot
Classifier: Programming Language :: Python :: 3.6
Classifier: Programming Language :: Python :: 3.7
Classifier: Programming Language :: Python :: 3.8
Classifier: License :: OSI Approved :: MIT License
Classifier: Operating System :: OS Independent
Requires-Python: >=3.6
License-File: LICENSE
